fastapi_modules/__init__.py
fastapi_modules/pydantic/__init__.py
fastapi_modules/pydantic/buonicovid.py
fastapi_modules/pydantic/ods.py
fastapi_modules/pydantic/ricvolantini.py
fastapi_modules/sqlalchemy/__init__.py
fastapi_modules/sqlalchemy/pgsql_buonicovid.py
fastapi_modules/sqlalchemy/pgsql_ods.py
fastapi_modules/sqlalchemy/pgsql_richiestevolantini.py
fastapi_modules-2.2.9.dist-info/LICENSE
fastapi_modules-2.2.9.dist-info/METADATA
fastapi_modules-2.2.9.dist-info/WHEEL
fastapi_modules-2.2.9.dist-info/top_level.txt
fastapi_modules-2.2.9.dist-info/RECORD
