Metadata-Version: 2.1
Name: fastapi-modules
Version: 2.2.9
Summary: Pacchetto per i modelli di fastapi sqlalchemy
Home-page: https://github.com/giaca95/Fastapi-modules
Author: Giacomo Callegaro
Author-email: giacomo_callegaro.95@libero.it
License: UNKNOWN
Download-URL: https://github.com/giaca95/Fastapi-modules.git
Platform: UNKNOWN
Classifier: Programming Language :: Python :: 3
Classifier: License :: OSI Approved :: MIT License
Classifier: Operating System :: OS Independent
Requires-Python: >=3.7
Requires-Dist: SQLAlchemy (>=1.3.22)
Requires-Dist: Pydantic (>=1.7.3)
